plotta/__init__.py
plotta-1.0.1a1.dist-info/DESCRIPTION.rst
plotta-1.0.1a1.dist-info/METADATA
plotta-1.0.1a1.dist-info/metadata.json
plotta-1.0.1a1.dist-info/RECORD
plotta-1.0.1a1.dist-info/top_level.txt
plotta-1.0.1a1.dist-info/WHEEL
