Metadata-Version: 2.0
Name: plotta
Version: 1.0.1a1
Summary: Python wrapper for Plotta API
Home-page: https://github.com/gzuidhof/plotta-python
Author: Guido Zuidhof
Author-email: me@guido.io
License: MIT
Keywords: plot plotting plotta
Platform: UNKNOWN
Classifier: Development Status :: 3 - Alpha
Classifier: Intended Audience :: Developers
Classifier: License :: OSI Approved :: MIT License
Requires-Dist: unirest
